banditsdk/__init__.py
banditsdk/common/__init__.py
banditsdk/common/code_speed_test.py
banditsdk/common/result.py
banditsdk/common/session/__init__.py
banditsdk/common/session/session_manager.py
banditsdk/http/__init__.py
banditsdk/http/http_result.py
banditsdk/http/status.py
banditsdk/http/web_result.py
banditsdk/http/exc/__init__.py
banditsdk/http/exc/http_exc.py
banditsdk/math/__init__.py
banditsdk/math/nums.py
banditsdk-0.2.1.dist-info/LICENSE
banditsdk-0.2.1.dist-info/METADATA
banditsdk-0.2.1.dist-info/WHEEL
banditsdk-0.2.1.dist-info/top_level.txt
banditsdk-0.2.1.dist-info/RECORD
