Metadata-Version: 2.1
Name: banditsdk
Version: 0.2.1
Summary: Common usage tools
Home-page: https://github.com/4ngry-GitHub/banditsdk
Author: 4ngry
Author-email: 4ngry24@gmail.com
Project-URL: Bug Tracker, https://github.com/4ngry-GitHub/banditsdk/issues
Requires-Python: >=3.8
License-File: LICENSE
Requires-Dist: pydantic
Requires-Dist: sqlalchemy
Requires-Dist: importlib-metadata ; python_version >= "3.8"
